swift_block/Parser.py
swift_block/RuleManager.py
swift_block/__init__.py
swift_block/main.py
swift_block/assets/active_shield.svg
swift_block/assets/app_icon.svg
swift_block/assets/autumn.png
swift_block/assets/github.svg
swift_block/assets/home.svg
swift_block/assets/inactive_shield.svg
swift_block/assets/license.png
swift_block/assets/martini.png
swift_block/assets/ruleMan.svg
swift_block/assets/sources_update.png
swift_block/assets/uninstall.png
swift_block/elevate/__init__.py
swift_block/elevate/posix.py
swift_block/elevate/windows.py
swift_block/ui/adblock.ui
swift_block/ui/filters.ui
swift_block-0.3.1.dist-info/LICENSE
swift_block-0.3.1.dist-info/METADATA
swift_block-0.3.1.dist-info/WHEEL
swift_block-0.3.1.dist-info/entry_points.txt
swift_block-0.3.1.dist-info/top_level.txt
swift_block-0.3.1.dist-info/RECORD
