Metadata-Version: 2.1
Name: swift-block
Version: 0.3.1
Summary: Swiftblock is a free and open-source hosts file based ad,malware and tracker blocker
Home-page: https://github.com/XploreInfinity/swift-block
Author: Xploreinfinity
License: GPLv3
Project-URL: Bug Tracker, https://github.com/XploreInfinity/swift-block/issues
Classifier: Programming Language :: Python :: 3
Classifier: License :: OSI Approved :: GNU General Public License v3 (GPLv3)
Classifier: Operating System :: POSIX :: Linux
Classifier: Operating System :: Microsoft :: Windows
Classifier: Operating System :: MacOS :: MacOS X
Classifier: Operating System :: POSIX :: BSD :: FreeBSD
Requires-Python: >=3.6
License-File: LICENSE
Requires-Dist: pyqt6 (>=6.2.2)
Requires-Dist: requests
Requires-Dist: winshell ; sys_platform == "win32"
Requires-Dist: pywin32 ; sys_platform == "win32"
